[
    {
        "model": "mywatchlist.mywatchlist",
        "pk": 1,
        "fields": {
            "watched": true,
            "title": "Film 1",
            "rating": "5",
            "release_date": "2010-01-01",
            "review": "Nice"
        }
    },
    {
        "model": "mywatchlist.mywatchlist",
        "pk": 2,
        "fields": {
            "watched": true,
            "title": "Film 2",
            "rating": "5",
            "release_date": "2011-01-01",
            "review": "Nice"
        }
    },
    {
        "model": "mywatchlist.mywatchlist",
        "pk": 3,
        "fields": {
            "watched": true,
            "title": "Film 3",
            "rating": "5",
            "release_date": "2012-01-01",
            "review": "Nice"
        }
    },
    {
        "model": "mywatchlist.mywatchlist",
        "pk": 4,
        "fields": {
            "watched": true,
            "title": "Film 4",
            "rating": "5",
            "release_date": "2013-01-01",
            "review": "Nice"
        }
    },
    {
        "model": "mywatchlist.mywatchlist",
        "pk": 5,
        "fields": {
            "watched": false,
            "title": "Film 5",
            "rating": "5",
            "release_date": "2014-01-01",
            "review": "Nice"
        }
    },
    {
        "model": "mywatchlist.mywatchlist",
        "pk": 6,
        "fields": {
            "watched": false,
            "title": "Film 6",
            "rating": "5",
            "release_date": "2015-01-01",
            "review": "Nice"
        }
    },
    {
        "model": "mywatchlist.mywatchlist",
        "pk": 7,
        "fields": {
            "watched": false,
            "title": "Film 7",
            "rating": "5",
            "release_date": "2016-01-01",
            "review": "Nice"
        }
    },
    {
        "model": "mywatchlist.mywatchlist",
        "pk": 8,
        "fields": {
            "watched": true,
            "title": "Film 8",
            "rating": "5",
            "release_date": "2017-01-01",
            "review": "Nice"
        }
    },
    {
        "model": "mywatchlist.mywatchlist",
        "pk": 9,
        "fields": {
            "watched": true,
            "title": "Film 9",
            "rating": "5",
            "release_date": "2018-01-01",
            "review": "Nice"
        }
    },
    {
        "model": "mywatchlist.mywatchlist",
        "pk": 10,
        "fields": {
            "watched": true,
            "title": "Film 10",
            "rating": "5",
            "release_date": "2019-01-01",
            "review": "Nice"
        }
    }
]